jupyterlab_gather/__init__.py
jupyterlab_gather/_version.py
jupyterlab_gather-0.1.3.data/data/share/jupyter/labextensions/jupyterlab_gather/package.json
jupyterlab_gather-0.1.3.data/data/share/jupyter/labextensions/jupyterlab_gather/schemas/jupyterlab_gather/package.json.orig
jupyterlab_gather-0.1.3.data/data/share/jupyter/labextensions/jupyterlab_gather/schemas/jupyterlab_gather/plugin.json
jupyterlab_gather-0.1.3.data/data/share/jupyter/labextensions/jupyterlab_gather/static/214.4179e9d19f19feb9e428.js
jupyterlab_gather-0.1.3.data/data/share/jupyter/labextensions/jupyterlab_gather/static/217.e224031ceab3bdb5ea84.js
jupyterlab_gather-0.1.3.data/data/share/jupyter/labextensions/jupyterlab_gather/static/233.b1fb4a051f2746fb9a34.js
jupyterlab_gather-0.1.3.data/data/share/jupyter/labextensions/jupyterlab_gather/static/298.a002297c70fb2b34fa0a.js
jupyterlab_gather-0.1.3.data/data/share/jupyter/labextensions/jupyterlab_gather/static/388.9cb15ad4a03b9cca43fb.js
jupyterlab_gather-0.1.3.data/data/share/jupyter/labextensions/jupyterlab_gather/static/403.e2320d9b9dd77bd2f9a4.js
jupyterlab_gather-0.1.3.data/data/share/jupyter/labextensions/jupyterlab_gather/static/451.ecad1f920b77ba8fedcb.js
jupyterlab_gather-0.1.3.data/data/share/jupyter/labextensions/jupyterlab_gather/static/487.015fea6d60cdf3bbb61f.js
jupyterlab_gather-0.1.3.data/data/share/jupyter/labextensions/jupyterlab_gather/static/487.015fea6d60cdf3bbb61f.js.LICENSE.txt
jupyterlab_gather-0.1.3.data/data/share/jupyter/labextensions/jupyterlab_gather/static/492.66b05a9cdf4876dc5d20.js
jupyterlab_gather-0.1.3.data/data/share/jupyter/labextensions/jupyterlab_gather/static/541.96fa8adb64140c0f9c7a.js
jupyterlab_gather-0.1.3.data/data/share/jupyter/labextensions/jupyterlab_gather/static/541.96fa8adb64140c0f9c7a.js.LICENSE.txt
jupyterlab_gather-0.1.3.data/data/share/jupyter/labextensions/jupyterlab_gather/static/554.f53f7921dc83b5a33c10.js
jupyterlab_gather-0.1.3.dist-info/METADATA
jupyterlab_gather-0.1.3.dist-info/WHEEL
jupyterlab_gather-0.1.3.dist-info/licenses/LICENSE
jupyterlab_gather-0.1.3.dist-info/RECORD
