Metadata-Version: 2.4
Name: jupyterlab_gather
Version: 0.1.3
Dynamic: Keywords
Summary: Video presentation over WebRTC with AR capabilities.
Project-URL: Homepage, https://github.com/QuantStack/jupyterlab-gather
Project-URL: Bug Tracker, https://github.com/QuantStack/jupyterlab-gather/issues
Project-URL: Repository, https://github.com/QuantStack/jupyterlab-gather.git
Author-email: Greg Mooney <gregory.mooney@quantstack.net>
License: BSD 3-Clause License
License-File: LICENSE
Classifier: Framework :: Jupyter
Classifier: Framework :: Jupyter :: JupyterLab
Classifier: Framework :: Jupyter :: JupyterLab :: 4
Classifier: Framework :: Jupyter :: JupyterLab :: Extensions
Classifier: Framework :: Jupyter :: JupyterLab :: Extensions :: Prebuilt
Classifier: License :: OSI Approved :: BSD License
Classifier: Programming Language :: Python
Classifier: Programming Language :: Python :: 3
Classifier: Programming Language :: Python :: 3.8
Classifier: Programming Language :: Python :: 3.9
Classifier: Programming Language :: Python :: 3.10
Classifier: Programming Language :: Python :: 3.11
Classifier: Programming Language :: Python :: 3.12
Requires-Python: >=3.8
Requires-Dist: jupyter-server<3,>=2.0.1
Requires-Dist: pyjwt
